Netaxgenesp/__init__.py
Netaxgenesp/network.cpython-311-darwin.so
Netaxgenesp-0.1.1.dist-info/LICENSE.txt
Netaxgenesp-0.1.1.dist-info/METADATA
Netaxgenesp-0.1.1.dist-info/WHEEL
Netaxgenesp-0.1.1.dist-info/top_level.txt
Netaxgenesp-0.1.1.dist-info/RECORD
