Metadata-Version: 2.1
Name: Netaxgenesp
Version: 0.1.1
Summary: A package for generating network files
Classifier: Programming Language :: Python :: 3
Classifier: Programming Language :: Python :: 3.7
Classifier: Programming Language :: Python :: 3.8
Classifier: Programming Language :: Python :: 3.9
License-File: LICENSE.txt
